linkedin_jobs_scraper/__init__.py
linkedin_jobs_scraper/config.py
linkedin_jobs_scraper/linkedin_scraper.py
linkedin_jobs_scraper/events/__init__.py
linkedin_jobs_scraper/events/events.py
linkedin_jobs_scraper/exceptions/__init__.py
linkedin_jobs_scraper/exceptions/exceptions.py
linkedin_jobs_scraper/filters/__init__.py
linkedin_jobs_scraper/filters/filters.py
linkedin_jobs_scraper/query/__init__.py
linkedin_jobs_scraper/query/query.py
linkedin_jobs_scraper/strategies/__init__.py
linkedin_jobs_scraper/strategies/anonymous_strategy.py
linkedin_jobs_scraper/strategies/authenticated_strategy.py
linkedin_jobs_scraper/strategies/strategy.py
linkedin_jobs_scraper/utils/__init__.py
linkedin_jobs_scraper/utils/chrome_driver.py
linkedin_jobs_scraper/utils/constants.py
linkedin_jobs_scraper/utils/logger.py
linkedin_jobs_scraper/utils/text.py
linkedin_jobs_scraper/utils/url.py
linkedin_jobs_scraper/utils/user_agent.py
linkedin_jobs_scraper-5.0.2.dist-info/LICENSE
linkedin_jobs_scraper-5.0.2.dist-info/METADATA
linkedin_jobs_scraper-5.0.2.dist-info/WHEEL
linkedin_jobs_scraper-5.0.2.dist-info/top_level.txt
linkedin_jobs_scraper-5.0.2.dist-info/RECORD
