Metadata-Version: 2.1
Name: linkedin-jobs-scraper
Version: 5.0.2
Summary: Scrape public available jobs on Linkedin using headless browser
Home-page: https://github.com/spinlud/py-linkedin-jobs-scraper.git
Author: Ludovico Fabbri
Author-email: ludovico.fabbri@gmail.com
License: UNKNOWN
Platform: UNKNOWN
Classifier: Intended Audience :: Developers
Classifier: Programming Language :: Python
Classifier: Programming Language :: Python :: 3.7
Classifier: Programming Language :: Python :: 3.8
Classifier: Programming Language :: Python :: 3.9
Classifier: Programming Language :: Python :: 3.10
Classifier: Programming Language :: Python :: 3.11
Classifier: Programming Language :: Python :: 3.12
Classifier: License :: OSI Approved :: MIT License
Classifier: Operating System :: OS Independent
Requires-Python: >=3.7
License-File: LICENSE
